<?xml version="1.0" encoding="UTF-8"?>
<?xml-stylesheet href="CoreNLP-to-HTML.xsl" type="text/xsl"?>
<root>
  <document>
    <docId>67AD5C9B.text</docId>
    <sentences>
      <sentence id="1">
        <tokens>
          <token id="1">
            <word>Latinos</word>
            <lemma>Latinos</lemma>
            <CharacterOffsetBegin>0</CharacterOffsetBegin>
            <CharacterOffsetEnd>7</CharacterOffsetEnd>
            <POS>NNPS</POS>
            <NER>O</NER>
          </token>
          <token id="2">
            <word>are</word>
            <lemma>be</lemma>
            <CharacterOffsetBegin>8</CharacterOffsetBegin>
            <CharacterOffsetEnd>11</CharacterOffsetEnd>
            <POS>VBP</POS>
            <NER>O</NER>
          </token>
          <token id="3">
            <word>a</word>
            <lemma>a</lemma>
            <CharacterOffsetBegin>12</CharacterOffsetBegin>
            <CharacterOffsetEnd>13</CharacterOffsetEnd>
            <POS>DT</POS>
            <NER>O</NER>
          </token>
          <token id="4">
            <word>thing</word>
            <lemma>thing</lemma>
            <CharacterOffsetBegin>14</CharacterOffsetBegin>
            <CharacterOffsetEnd>19</CharacterOffsetEnd>
            <POS>NN</POS>
            <NER>O</NER>
          </token>
          <token id="5">
            <word>in</word>
            <lemma>in</lemma>
            <CharacterOffsetBegin>20</CharacterOffsetBegin>
            <CharacterOffsetEnd>22</CharacterOffsetEnd>
            <POS>IN</POS>
            <NER>O</NER>
          </token>
          <token id="6">
            <word>the</word>
            <lemma>the</lemma>
            <CharacterOffsetBegin>23</CharacterOffsetBegin>
            <CharacterOffsetEnd>26</CharacterOffsetEnd>
            <POS>DT</POS>
            <NER>O</NER>
          </token>
          <token id="7">
            <word>united</word>
            <lemma>united</lemma>
            <CharacterOffsetBegin>27</CharacterOffsetBegin>
            <CharacterOffsetEnd>33</CharacterOffsetEnd>
            <POS>JJ</POS>
            <NER>COUNTRY</NER>
          </token>
          <token id="8">
            <word>states</word>
            <lemma>state</lemma>
            <CharacterOffsetBegin>34</CharacterOffsetBegin>
            <CharacterOffsetEnd>40</CharacterOffsetEnd>
            <POS>NNS</POS>
            <NER>COUNTRY</NER>
          </token>
          <token id="9">
            <word>of</word>
            <lemma>of</lemma>
            <CharacterOffsetBegin>41</CharacterOffsetBegin>
            <CharacterOffsetEnd>43</CharacterOffsetEnd>
            <POS>IN</POS>
            <NER>COUNTRY</NER>
          </token>
          <token id="10">
            <word>america</word>
            <lemma>america</lemma>
            <CharacterOffsetBegin>44</CharacterOffsetBegin>
            <CharacterOffsetEnd>51</CharacterOffsetEnd>
            <POS>NN</POS>
            <NER>COUNTRY</NER>
          </token>
          <token id="11">
            <word>but</word>
            <lemma>but</lemma>
            <CharacterOffsetBegin>52</CharacterOffsetBegin>
            <CharacterOffsetEnd>55</CharacterOffsetEnd>
            <POS>CC</POS>
            <NER>O</NER>
          </token>
          <token id="12">
            <word>you</word>
            <lemma>you</lemma>
            <CharacterOffsetBegin>56</CharacterOffsetBegin>
            <CharacterOffsetEnd>59</CharacterOffsetEnd>
            <POS>PRP</POS>
            <NER>O</NER>
          </token>
          <token id="13">
            <word>will</word>
            <lemma>will</lemma>
            <CharacterOffsetBegin>60</CharacterOffsetBegin>
            <CharacterOffsetEnd>64</CharacterOffsetEnd>
            <POS>MD</POS>
            <NER>O</NER>
          </token>
          <token id="14">
            <word>never</word>
            <lemma>never</lemma>
            <CharacterOffsetBegin>65</CharacterOffsetBegin>
            <CharacterOffsetEnd>70</CharacterOffsetEnd>
            <POS>RB</POS>
            <NER>O</NER>
          </token>
          <token id="15">
            <word>see</word>
            <lemma>see</lemma>
            <CharacterOffsetBegin>71</CharacterOffsetBegin>
            <CharacterOffsetEnd>74</CharacterOffsetEnd>
            <POS>VB</POS>
            <NER>O</NER>
          </token>
          <token id="16">
            <word>a</word>
            <lemma>a</lemma>
            <CharacterOffsetBegin>75</CharacterOffsetBegin>
            <CharacterOffsetEnd>76</CharacterOffsetEnd>
            <POS>DT</POS>
            <NER>O</NER>
          </token>
          <token id="17">
            <word>spanish</word>
            <lemma>spanish</lemma>
            <CharacterOffsetBegin>77</CharacterOffsetBegin>
            <CharacterOffsetEnd>84</CharacterOffsetEnd>
            <POS>NNP</POS>
            <NER>NATIONALITY</NER>
          </token>
          <token id="18">
            <word>/</word>
            <lemma>/</lemma>
            <CharacterOffsetBegin>84</CharacterOffsetBegin>
            <CharacterOffsetEnd>85</CharacterOffsetEnd>
            <POS>,</POS>
            <NER>O</NER>
          </token>
          <token id="19">
            <word>french</word>
            <lemma>french</lemma>
            <CharacterOffsetBegin>85</CharacterOffsetBegin>
            <CharacterOffsetEnd>91</CharacterOffsetEnd>
            <POS>JJ</POS>
            <NER>NATIONALITY</NER>
          </token>
          <token id="20">
            <word>/</word>
            <lemma>/</lemma>
            <CharacterOffsetBegin>91</CharacterOffsetBegin>
            <CharacterOffsetEnd>92</CharacterOffsetEnd>
            <POS>HYPH</POS>
            <NER>O</NER>
          </token>
          <token id="21">
            <word>italian</word>
            <lemma>italian</lemma>
            <CharacterOffsetBegin>92</CharacterOffsetBegin>
            <CharacterOffsetEnd>99</CharacterOffsetEnd>
            <POS>JJ</POS>
            <NER>NATIONALITY</NER>
          </token>
          <token id="22">
            <word>/</word>
            <lemma>/</lemma>
            <CharacterOffsetBegin>99</CharacterOffsetBegin>
            <CharacterOffsetEnd>100</CharacterOffsetEnd>
            <POS>HYPH</POS>
            <NER>O</NER>
          </token>
          <token id="23">
            <word>romanian</word>
            <lemma>romanian</lemma>
            <CharacterOffsetBegin>100</CharacterOffsetBegin>
            <CharacterOffsetEnd>108</CharacterOffsetEnd>
            <POS>JJ</POS>
            <NER>NATIONALITY</NER>
          </token>
          <token id="24">
            <word>person</word>
            <lemma>person</lemma>
            <CharacterOffsetBegin>109</CharacterOffsetBegin>
            <CharacterOffsetEnd>115</CharacterOffsetEnd>
            <POS>NN</POS>
            <NER>O</NER>
          </token>
          <token id="25">
            <word>called</word>
            <lemma>call</lemma>
            <CharacterOffsetBegin>116</CharacterOffsetBegin>
            <CharacterOffsetEnd>122</CharacterOffsetEnd>
            <POS>VBD</POS>
            <NER>O</NER>
          </token>
          <token id="26">
            <word>a</word>
            <lemma>a</lemma>
            <CharacterOffsetBegin>123</CharacterOffsetBegin>
            <CharacterOffsetEnd>124</CharacterOffsetEnd>
            <POS>DT</POS>
            <NER>O</NER>
          </token>
          <token id="27">
            <word>latino</word>
            <lemma>latino</lemma>
            <CharacterOffsetBegin>125</CharacterOffsetBegin>
            <CharacterOffsetEnd>131</CharacterOffsetEnd>
            <POS>NN</POS>
            <NER>O</NER>
          </token>
          <token id="28">
            <word>/</word>
            <lemma>/</lemma>
            <CharacterOffsetBegin>131</CharacterOffsetBegin>
            <CharacterOffsetEnd>132</CharacterOffsetEnd>
            <POS>HYPH</POS>
            <NER>O</NER>
          </token>
          <token id="29">
            <word>a</word>
            <lemma>a</lemma>
            <CharacterOffsetBegin>132</CharacterOffsetBegin>
            <CharacterOffsetEnd>133</CharacterOffsetEnd>
            <POS>DT</POS>
            <NER>O</NER>
          </token>
          <token id="30">
            <word>too</word>
            <lemma>too</lemma>
            <CharacterOffsetBegin>134</CharacterOffsetBegin>
            <CharacterOffsetEnd>137</CharacterOffsetEnd>
            <POS>RB</POS>
            <NER>O</NER>
          </token>
          <token id="31">
            <word>,</word>
            <lemma>,</lemma>
            <CharacterOffsetBegin>137</CharacterOffsetBegin>
            <CharacterOffsetEnd>138</CharacterOffsetEnd>
            <POS>,</POS>
            <NER>O</NER>
          </token>
          <token id="32">
            <word>that</word>
            <lemma>that</lemma>
            <CharacterOffsetBegin>139</CharacterOffsetBegin>
            <CharacterOffsetEnd>143</CharacterOffsetEnd>
            <POS>DT</POS>
            <NER>O</NER>
          </token>
          <token id="33">
            <word>'s</word>
            <lemma>be</lemma>
            <CharacterOffsetBegin>143</CharacterOffsetBegin>
            <CharacterOffsetEnd>145</CharacterOffsetEnd>
            <POS>VBZ</POS>
            <NER>O</NER>
          </token>
          <token id="34">
            <word>just</word>
            <lemma>just</lemma>
            <CharacterOffsetBegin>146</CharacterOffsetBegin>
            <CharacterOffsetEnd>150</CharacterOffsetEnd>
            <POS>RB</POS>
            <NER>O</NER>
          </token>
          <token id="35">
            <word>stupid</word>
            <lemma>stupid</lemma>
            <CharacterOffsetBegin>151</CharacterOffsetBegin>
            <CharacterOffsetEnd>157</CharacterOffsetEnd>
            <POS>JJ</POS>
            <NER>O</NER>
          </token>
          <token id="36">
            <word>.</word>
            <lemma>.</lemma>
            <CharacterOffsetBegin>157</CharacterOffsetBegin>
            <CharacterOffsetEnd>158</CharacterOffsetEnd>
            <POS>.</POS>
            <NER>O</NER>
          </token>
        </tokens>
        <parse>(ROOT (S (S (NP (NNPS Latinos)) (VP (VBP are) (NP (NP (DT a) (NN thing)) (PP (IN in) (NP (NP (DT the) (JJ united) (NNS states)) (PP (IN of) (NP (NN america)))))))) (CC but) (S (S (NP (PRP you)) (VP (MD will) (ADVP (RB never)) (VP (VB see) (NP (DT a) (NNP spanish))))) (, /) (S (NP (ADJP (NP (JJ french) (HYPH /) (JJ italian)) (HYPH /) (JJ romanian)) (NN person)) (VP (VBD called) (NP (DT a) (NN latino) (HYPH /)) (ADVP (DT a) (RB too)))) (, ,) (S (NP (DT that)) (VP (VBZ 's) (ADJP (RB just) (JJ stupid))))) (. .))) </parse>
        <dependencies type="basic-dependencies">
          <dep type="root">
            <governor idx="0">ROOT</governor>
            <dependent idx="4">thing</dependent>
          </dep>
          <dep type="nsubj">
            <governor idx="4">thing</governor>
            <dependent idx="1">Latinos</dependent>
          </dep>
          <dep type="cop">
            <governor idx="4">thing</governor>
            <dependent idx="2">are</dependent>
          </dep>
          <dep type="det">
            <governor idx="4">thing</governor>
            <dependent idx="3">a</dependent>
          </dep>
          <dep type="case">
            <governor idx="8">states</governor>
            <dependent idx="5">in</dependent>
          </dep>
          <dep type="det">
            <governor idx="8">states</governor>
            <dependent idx="6">the</dependent>
          </dep>
          <dep type="amod">
            <governor idx="8">states</governor>
            <dependent idx="7">united</dependent>
          </dep>
          <dep type="nmod">
            <governor idx="4">thing</governor>
            <dependent idx="8">states</dependent>
          </dep>
          <dep type="case">
            <governor idx="10">america</governor>
            <dependent idx="9">of</dependent>
          </dep>
          <dep type="nmod">
            <governor idx="8">states</governor>
            <dependent idx="10">america</dependent>
          </dep>
          <dep type="cc">
            <governor idx="15">see</governor>
            <dependent idx="11">but</dependent>
          </dep>
          <dep type="nsubj">
            <governor idx="15">see</governor>
            <dependent idx="12">you</dependent>
          </dep>
          <dep type="aux">
            <governor idx="15">see</governor>
            <dependent idx="13">will</dependent>
          </dep>
          <dep type="advmod">
            <governor idx="15">see</governor>
            <dependent idx="14">never</dependent>
          </dep>
          <dep type="conj">
            <governor idx="4">thing</governor>
            <dependent idx="15">see</dependent>
          </dep>
          <dep type="det">
            <governor idx="17">spanish</governor>
            <dependent idx="16">a</dependent>
          </dep>
          <dep type="obj">
            <governor idx="15">see</governor>
            <dependent idx="17">spanish</dependent>
          </dep>
          <dep type="punct">
            <governor idx="15">see</governor>
            <dependent idx="18">/</dependent>
          </dep>
          <dep type="amod">
            <governor idx="21">italian</governor>
            <dependent idx="19">french</dependent>
          </dep>
          <dep type="punct">
            <governor idx="21">italian</governor>
            <dependent idx="20">/</dependent>
          </dep>
          <dep type="dep">
            <governor idx="23">romanian</governor>
            <dependent idx="21">italian</dependent>
          </dep>
          <dep type="punct">
            <governor idx="23">romanian</governor>
            <dependent idx="22">/</dependent>
          </dep>
          <dep type="amod">
            <governor idx="24">person</governor>
            <dependent idx="23">romanian</dependent>
          </dep>
          <dep type="nsubj">
            <governor idx="25">called</governor>
            <dependent idx="24">person</dependent>
          </dep>
          <dep type="conj">
            <governor idx="15">see</governor>
            <dependent idx="25">called</dependent>
          </dep>
          <dep type="det">
            <governor idx="27">latino</governor>
            <dependent idx="26">a</dependent>
          </dep>
          <dep type="obj">
            <governor idx="25">called</governor>
            <dependent idx="27">latino</dependent>
          </dep>
          <dep type="punct">
            <governor idx="27">latino</governor>
            <dependent idx="28">/</dependent>
          </dep>
          <dep type="dep">
            <governor idx="30">too</governor>
            <dependent idx="29">a</dependent>
          </dep>
          <dep type="advmod">
            <governor idx="25">called</governor>
            <dependent idx="30">too</dependent>
          </dep>
          <dep type="punct">
            <governor idx="15">see</governor>
            <dependent idx="31">,</dependent>
          </dep>
          <dep type="nsubj">
            <governor idx="35">stupid</governor>
            <dependent idx="32">that</dependent>
          </dep>
          <dep type="cop">
            <governor idx="35">stupid</governor>
            <dependent idx="33">'s</dependent>
          </dep>
          <dep type="advmod">
            <governor idx="35">stupid</governor>
            <dependent idx="34">just</dependent>
          </dep>
          <dep type="parataxis">
            <governor idx="15">see</governor>
            <dependent idx="35">stupid</dependent>
          </dep>
          <dep type="punct">
            <governor idx="4">thing</governor>
            <dependent idx="36">.</dependent>
          </dep>
        </dependencies>
        <dependencies type="collapsed-dependencies">
          <dep type="root">
            <governor idx="0">ROOT</governor>
            <dependent idx="4">thing</dependent>
          </dep>
          <dep type="nsubj">
            <governor idx="4">thing</governor>
            <dependent idx="1">Latinos</dependent>
          </dep>
          <dep type="cop">
            <governor idx="4">thing</governor>
            <dependent idx="2">are</dependent>
          </dep>
          <dep type="det">
            <governor idx="4">thing</governor>
            <dependent idx="3">a</dependent>
          </dep>
          <dep type="case">
            <governor idx="8">states</governor>
            <dependent idx="5">in</dependent>
          </dep>
          <dep type="det">
            <governor idx="8">states</governor>
            <dependent idx="6">the</dependent>
          </dep>
          <dep type="amod">
            <governor idx="8">states</governor>
            <dependent idx="7">united</dependent>
          </dep>
          <dep type="nmod:in">
            <governor idx="4">thing</governor>
            <dependent idx="8">states</dependent>
          </dep>
          <dep type="case">
            <governor idx="10">america</governor>
            <dependent idx="9">of</dependent>
          </dep>
          <dep type="nmod:of">
            <governor idx="8">states</governor>
            <dependent idx="10">america</dependent>
          </dep>
          <dep type="cc">
            <governor idx="15">see</governor>
            <dependent idx="11">but</dependent>
          </dep>
          <dep type="nsubj">
            <governor idx="15">see</governor>
            <dependent idx="12">you</dependent>
          </dep>
          <dep type="aux">
            <governor idx="15">see</governor>
            <dependent idx="13">will</dependent>
          </dep>
          <dep type="advmod">
            <governor idx="15">see</governor>
            <dependent idx="14">never</dependent>
          </dep>
          <dep type="conj:but">
            <governor idx="4">thing</governor>
            <dependent idx="15">see</dependent>
          </dep>
          <dep type="det">
            <governor idx="17">spanish</governor>
            <dependent idx="16">a</dependent>
          </dep>
          <dep type="obj">
            <governor idx="15">see</governor>
            <dependent idx="17">spanish</dependent>
          </dep>
          <dep type="punct">
            <governor idx="15">see</governor>
            <dependent idx="18">/</dependent>
          </dep>
          <dep type="amod">
            <governor idx="21">italian</governor>
            <dependent idx="19">french</dependent>
          </dep>
          <dep type="punct">
            <governor idx="21">italian</governor>
            <dependent idx="20">/</dependent>
          </dep>
          <dep type="dep">
            <governor idx="23">romanian</governor>
            <dependent idx="21">italian</dependent>
          </dep>
          <dep type="punct">
            <governor idx="23">romanian</governor>
            <dependent idx="22">/</dependent>
          </dep>
          <dep type="amod">
            <governor idx="24">person</governor>
            <dependent idx="23">romanian</dependent>
          </dep>
          <dep type="nsubj">
            <governor idx="25">called</governor>
            <dependent idx="24">person</dependent>
          </dep>
          <dep type="conj">
            <governor idx="15">see</governor>
            <dependent idx="25">called</dependent>
          </dep>
          <dep type="det">
            <governor idx="27">latino</governor>
            <dependent idx="26">a</dependent>
          </dep>
          <dep type="obj">
            <governor idx="25">called</governor>
            <dependent idx="27">latino</dependent>
          </dep>
          <dep type="punct">
            <governor idx="27">latino</governor>
            <dependent idx="28">/</dependent>
          </dep>
          <dep type="dep">
            <governor idx="30">too</governor>
            <dependent idx="29">a</dependent>
          </dep>
          <dep type="advmod">
            <governor idx="25">called</governor>
            <dependent idx="30">too</dependent>
          </dep>
          <dep type="punct">
            <governor idx="15">see</governor>
            <dependent idx="31">,</dependent>
          </dep>
          <dep type="nsubj">
            <governor idx="35">stupid</governor>
            <dependent idx="32">that</dependent>
          </dep>
          <dep type="cop">
            <governor idx="35">stupid</governor>
            <dependent idx="33">'s</dependent>
          </dep>
          <dep type="advmod">
            <governor idx="35">stupid</governor>
            <dependent idx="34">just</dependent>
          </dep>
          <dep type="parataxis">
            <governor idx="15">see</governor>
            <dependent idx="35">stupid</dependent>
          </dep>
          <dep type="punct">
            <governor idx="4">thing</governor>
            <dependent idx="36">.</dependent>
          </dep>
        </dependencies>
        <dependencies type="collapsed-ccprocessed-dependencies">
          <dep type="root">
            <governor idx="0">ROOT</governor>
            <dependent idx="4">thing</dependent>
          </dep>
          <dep type="nsubj">
            <governor idx="4">thing</governor>
            <dependent idx="1">Latinos</dependent>
          </dep>
          <dep type="cop">
            <governor idx="4">thing</governor>
            <dependent idx="2">are</dependent>
          </dep>
          <dep type="det">
            <governor idx="4">thing</governor>
            <dependent idx="3">a</dependent>
          </dep>
          <dep type="case">
            <governor idx="8">states</governor>
            <dependent idx="5">in</dependent>
          </dep>
          <dep type="det">
            <governor idx="8">states</governor>
            <dependent idx="6">the</dependent>
          </dep>
          <dep type="amod">
            <governor idx="8">states</governor>
            <dependent idx="7">united</dependent>
          </dep>
          <dep type="nmod:in">
            <governor idx="4">thing</governor>
            <dependent idx="8">states</dependent>
          </dep>
          <dep type="case">
            <governor idx="10">america</governor>
            <dependent idx="9">of</dependent>
          </dep>
          <dep type="nmod:of">
            <governor idx="8">states</governor>
            <dependent idx="10">america</dependent>
          </dep>
          <dep type="cc">
            <governor idx="15">see</governor>
            <dependent idx="11">but</dependent>
          </dep>
          <dep type="nsubj">
            <governor idx="15">see</governor>
            <dependent idx="12">you</dependent>
          </dep>
          <dep type="aux">
            <governor idx="15">see</governor>
            <dependent idx="13">will</dependent>
          </dep>
          <dep type="advmod">
            <governor idx="15">see</governor>
            <dependent idx="14">never</dependent>
          </dep>
          <dep type="conj:but">
            <governor idx="4">thing</governor>
            <dependent idx="15">see</dependent>
          </dep>
          <dep type="det">
            <governor idx="17">spanish</governor>
            <dependent idx="16">a</dependent>
          </dep>
          <dep type="obj">
            <governor idx="15">see</governor>
            <dependent idx="17">spanish</dependent>
          </dep>
          <dep type="punct">
            <governor idx="15">see</governor>
            <dependent idx="18">/</dependent>
          </dep>
          <dep type="amod">
            <governor idx="21">italian</governor>
            <dependent idx="19">french</dependent>
          </dep>
          <dep type="punct">
            <governor idx="21">italian</governor>
            <dependent idx="20">/</dependent>
          </dep>
          <dep type="dep">
            <governor idx="23">romanian</governor>
            <dependent idx="21">italian</dependent>
          </dep>
          <dep type="punct">
            <governor idx="23">romanian</governor>
            <dependent idx="22">/</dependent>
          </dep>
          <dep type="amod">
            <governor idx="24">person</governor>
            <dependent idx="23">romanian</dependent>
          </dep>
          <dep type="nsubj">
            <governor idx="25">called</governor>
            <dependent idx="24">person</dependent>
          </dep>
          <dep type="conj">
            <governor idx="15">see</governor>
            <dependent idx="25">called</dependent>
          </dep>
          <dep type="det">
            <governor idx="27">latino</governor>
            <dependent idx="26">a</dependent>
          </dep>
          <dep type="obj">
            <governor idx="25">called</governor>
            <dependent idx="27">latino</dependent>
          </dep>
          <dep type="punct">
            <governor idx="27">latino</governor>
            <dependent idx="28">/</dependent>
          </dep>
          <dep type="dep">
            <governor idx="30">too</governor>
            <dependent idx="29">a</dependent>
          </dep>
          <dep type="advmod">
            <governor idx="25">called</governor>
            <dependent idx="30">too</dependent>
          </dep>
          <dep type="punct">
            <governor idx="15">see</governor>
            <dependent idx="31">,</dependent>
          </dep>
          <dep type="nsubj">
            <governor idx="35">stupid</governor>
            <dependent idx="32">that</dependent>
          </dep>
          <dep type="cop">
            <governor idx="35">stupid</governor>
            <dependent idx="33">'s</dependent>
          </dep>
          <dep type="advmod">
            <governor idx="35">stupid</governor>
            <dependent idx="34">just</dependent>
          </dep>
          <dep type="parataxis">
            <governor idx="15">see</governor>
            <dependent idx="35">stupid</dependent>
          </dep>
          <dep type="punct">
            <governor idx="4">thing</governor>
            <dependent idx="36">.</dependent>
          </dep>
        </dependencies>
        <dependencies type="enhanced-dependencies">
          <dep type="root">
            <governor idx="0">ROOT</governor>
            <dependent idx="4">thing</dependent>
          </dep>
          <dep type="nsubj">
            <governor idx="4">thing</governor>
            <dependent idx="1">Latinos</dependent>
          </dep>
          <dep type="cop">
            <governor idx="4">thing</governor>
            <dependent idx="2">are</dependent>
          </dep>
          <dep type="det">
            <governor idx="4">thing</governor>
            <dependent idx="3">a</dependent>
          </dep>
          <dep type="case">
            <governor idx="8">states</governor>
            <dependent idx="5">in</dependent>
          </dep>
          <dep type="det">
            <governor idx="8">states</governor>
            <dependent idx="6">the</dependent>
          </dep>
          <dep type="amod">
            <governor idx="8">states</governor>
            <dependent idx="7">united</dependent>
          </dep>
          <dep type="nmod:in">
            <governor idx="4">thing</governor>
            <dependent idx="8">states</dependent>
          </dep>
          <dep type="case">
            <governor idx="10">america</governor>
            <dependent idx="9">of</dependent>
          </dep>
          <dep type="nmod:of">
            <governor idx="8">states</governor>
            <dependent idx="10">america</dependent>
          </dep>
          <dep type="cc">
            <governor idx="15">see</governor>
            <dependent idx="11">but</dependent>
          </dep>
          <dep type="nsubj">
            <governor idx="15">see</governor>
            <dependent idx="12">you</dependent>
          </dep>
          <dep type="aux">
            <governor idx="15">see</governor>
            <dependent idx="13">will</dependent>
          </dep>
          <dep type="advmod">
            <governor idx="15">see</governor>
            <dependent idx="14">never</dependent>
          </dep>
          <dep type="conj:but">
            <governor idx="4">thing</governor>
            <dependent idx="15">see</dependent>
          </dep>
          <dep type="det">
            <governor idx="17">spanish</governor>
            <dependent idx="16">a</dependent>
          </dep>
          <dep type="obj">
            <governor idx="15">see</governor>
            <dependent idx="17">spanish</dependent>
          </dep>
          <dep type="punct">
            <governor idx="15">see</governor>
            <dependent idx="18">/</dependent>
          </dep>
          <dep type="amod">
            <governor idx="21">italian</governor>
            <dependent idx="19">french</dependent>
          </dep>
          <dep type="punct">
            <governor idx="21">italian</governor>
            <dependent idx="20">/</dependent>
          </dep>
          <dep type="dep">
            <governor idx="23">romanian</governor>
            <dependent idx="21">italian</dependent>
          </dep>
          <dep type="punct">
            <governor idx="23">romanian</governor>
            <dependent idx="22">/</dependent>
          </dep>
          <dep type="amod">
            <governor idx="24">person</governor>
            <dependent idx="23">romanian</dependent>
          </dep>
          <dep type="nsubj">
            <governor idx="25">called</governor>
            <dependent idx="24">person</dependent>
          </dep>
          <dep type="conj">
            <governor idx="15">see</governor>
            <dependent idx="25">called</dependent>
          </dep>
          <dep type="det">
            <governor idx="27">latino</governor>
            <dependent idx="26">a</dependent>
          </dep>
          <dep type="obj">
            <governor idx="25">called</governor>
            <dependent idx="27">latino</dependent>
          </dep>
          <dep type="punct">
            <governor idx="27">latino</governor>
            <dependent idx="28">/</dependent>
          </dep>
          <dep type="dep">
            <governor idx="30">too</governor>
            <dependent idx="29">a</dependent>
          </dep>
          <dep type="advmod">
            <governor idx="25">called</governor>
            <dependent idx="30">too</dependent>
          </dep>
          <dep type="punct">
            <governor idx="15">see</governor>
            <dependent idx="31">,</dependent>
          </dep>
          <dep type="nsubj">
            <governor idx="35">stupid</governor>
            <dependent idx="32">that</dependent>
          </dep>
          <dep type="cop">
            <governor idx="35">stupid</governor>
            <dependent idx="33">'s</dependent>
          </dep>
          <dep type="advmod">
            <governor idx="35">stupid</governor>
            <dependent idx="34">just</dependent>
          </dep>
          <dep type="parataxis">
            <governor idx="15">see</governor>
            <dependent idx="35">stupid</dependent>
          </dep>
          <dep type="punct">
            <governor idx="4">thing</governor>
            <dependent idx="36">.</dependent>
          </dep>
        </dependencies>
        <dependencies type="enhanced-plus-plus-dependencies">
          <dep type="root">
            <governor idx="0">ROOT</governor>
            <dependent idx="4">thing</dependent>
          </dep>
          <dep type="nsubj">
            <governor idx="4">thing</governor>
            <dependent idx="1">Latinos</dependent>
          </dep>
          <dep type="cop">
            <governor idx="4">thing</governor>
            <dependent idx="2">are</dependent>
          </dep>
          <dep type="det">
            <governor idx="4">thing</governor>
            <dependent idx="3">a</dependent>
          </dep>
          <dep type="case">
            <governor idx="8">states</governor>
            <dependent idx="5">in</dependent>
          </dep>
          <dep type="det">
            <governor idx="8">states</governor>
            <dependent idx="6">the</dependent>
          </dep>
          <dep type="amod">
            <governor idx="8">states</governor>
            <dependent idx="7">united</dependent>
          </dep>
          <dep type="nmod:in">
            <governor idx="4">thing</governor>
            <dependent idx="8">states</dependent>
          </dep>
          <dep type="case">
            <governor idx="10">america</governor>
            <dependent idx="9">of</dependent>
          </dep>
          <dep type="nmod:of">
            <governor idx="8">states</governor>
            <dependent idx="10">america</dependent>
          </dep>
          <dep type="cc">
            <governor idx="15">see</governor>
            <dependent idx="11">but</dependent>
          </dep>
          <dep type="nsubj">
            <governor idx="15">see</governor>
            <dependent idx="12">you</dependent>
          </dep>
          <dep type="aux">
            <governor idx="15">see</governor>
            <dependent idx="13">will</dependent>
          </dep>
          <dep type="advmod">
            <governor idx="15">see</governor>
            <dependent idx="14">never</dependent>
          </dep>
          <dep type="conj:but">
            <governor idx="4">thing</governor>
            <dependent idx="15">see</dependent>
          </dep>
          <dep type="det">
            <governor idx="17">spanish</governor>
            <dependent idx="16">a</dependent>
          </dep>
          <dep type="obj">
            <governor idx="15">see</governor>
            <dependent idx="17">spanish</dependent>
          </dep>
          <dep type="punct">
            <governor idx="15">see</governor>
            <dependent idx="18">/</dependent>
          </dep>
          <dep type="amod">
            <governor idx="21">italian</governor>
            <dependent idx="19">french</dependent>
          </dep>
          <dep type="punct">
            <governor idx="21">italian</governor>
            <dependent idx="20">/</dependent>
          </dep>
          <dep type="dep">
            <governor idx="23">romanian</governor>
            <dependent idx="21">italian</dependent>
          </dep>
          <dep type="punct">
            <governor idx="23">romanian</governor>
            <dependent idx="22">/</dependent>
          </dep>
          <dep type="amod">
            <governor idx="24">person</governor>
            <dependent idx="23">romanian</dependent>
          </dep>
          <dep type="nsubj">
            <governor idx="25">called</governor>
            <dependent idx="24">person</dependent>
          </dep>
          <dep type="conj">
            <governor idx="15">see</governor>
            <dependent idx="25">called</dependent>
          </dep>
          <dep type="det">
            <governor idx="27">latino</governor>
            <dependent idx="26">a</dependent>
          </dep>
          <dep type="obj">
            <governor idx="25">called</governor>
            <dependent idx="27">latino</dependent>
          </dep>
          <dep type="punct">
            <governor idx="27">latino</governor>
            <dependent idx="28">/</dependent>
          </dep>
          <dep type="dep">
            <governor idx="30">too</governor>
            <dependent idx="29">a</dependent>
          </dep>
          <dep type="advmod">
            <governor idx="25">called</governor>
            <dependent idx="30">too</dependent>
          </dep>
          <dep type="punct">
            <governor idx="15">see</governor>
            <dependent idx="31">,</dependent>
          </dep>
          <dep type="nsubj">
            <governor idx="35">stupid</governor>
            <dependent idx="32">that</dependent>
          </dep>
          <dep type="cop">
            <governor idx="35">stupid</governor>
            <dependent idx="33">'s</dependent>
          </dep>
          <dep type="advmod">
            <governor idx="35">stupid</governor>
            <dependent idx="34">just</dependent>
          </dep>
          <dep type="parataxis">
            <governor idx="15">see</governor>
            <dependent idx="35">stupid</dependent>
          </dep>
          <dep type="punct">
            <governor idx="4">thing</governor>
            <dependent idx="36">.</dependent>
          </dep>
        </dependencies>
      </sentence>
    </sentences>
  </document>
</root>
