<?xml version="1.0" encoding="UTF-8"?>
<?xml-stylesheet href="CoreNLP-to-HTML.xsl" type="text/xsl"?>
<root>
  <document>
    <docId>ED792340.text</docId>
    <sentences>
      <sentence id="1">
        <tokens>
          <token id="1">
            <word>Simple</word>
            <lemma>simple</lemma>
            <CharacterOffsetBegin>0</CharacterOffsetBegin>
            <CharacterOffsetEnd>6</CharacterOffsetEnd>
            <POS>JJ</POS>
            <NER>O</NER>
          </token>
          <token id="2">
            <word>genetics</word>
            <lemma>genetics</lemma>
            <CharacterOffsetBegin>7</CharacterOffsetBegin>
            <CharacterOffsetEnd>15</CharacterOffsetEnd>
            <POS>NN</POS>
            <NER>O</NER>
          </token>
          <token id="3">
            <word>...</word>
            <lemma>...</lemma>
            <CharacterOffsetBegin>15</CharacterOffsetBegin>
            <CharacterOffsetEnd>18</CharacterOffsetEnd>
            <POS>,</POS>
            <NER>O</NER>
          </token>
          <token id="4">
            <word>know</word>
            <lemma>know</lemma>
            <CharacterOffsetBegin>18</CharacterOffsetBegin>
            <CharacterOffsetEnd>22</CharacterOffsetEnd>
            <POS>VB</POS>
            <NER>O</NER>
          </token>
          <token id="5">
            <word>what</word>
            <lemma>what</lemma>
            <CharacterOffsetBegin>23</CharacterOffsetBegin>
            <CharacterOffsetEnd>27</CharacterOffsetEnd>
            <POS>WP</POS>
            <NER>O</NER>
          </token>
          <token id="6">
            <word>I</word>
            <lemma>I</lemma>
            <CharacterOffsetBegin>28</CharacterOffsetBegin>
            <CharacterOffsetEnd>29</CharacterOffsetEnd>
            <POS>PRP</POS>
            <NER>O</NER>
          </token>
          <token id="7">
            <word>mean</word>
            <lemma>mean</lemma>
            <CharacterOffsetBegin>30</CharacterOffsetBegin>
            <CharacterOffsetEnd>34</CharacterOffsetEnd>
            <POS>VBP</POS>
            <NER>O</NER>
          </token>
          <token id="8">
            <word>?</word>
            <lemma>?</lemma>
            <CharacterOffsetBegin>34</CharacterOffsetBegin>
            <CharacterOffsetEnd>35</CharacterOffsetEnd>
            <POS>.</POS>
            <NER>O</NER>
          </token>
        </tokens>
        <parse>(ROOT (FRAG (NP (JJ Simple) (NN genetics)) (, ...) (S (VP (VB know) (SBAR (WHNP (WP what)) (S (NP (PRP I)) (VP (VBP mean)))))) (. ?))) </parse>
        <dependencies type="basic-dependencies">
          <dep type="root">
            <governor idx="0">ROOT</governor>
            <dependent idx="2">genetics</dependent>
          </dep>
          <dep type="amod">
            <governor idx="2">genetics</governor>
            <dependent idx="1">Simple</dependent>
          </dep>
          <dep type="punct">
            <governor idx="2">genetics</governor>
            <dependent idx="3">...</dependent>
          </dep>
          <dep type="dep">
            <governor idx="2">genetics</governor>
            <dependent idx="4">know</dependent>
          </dep>
          <dep type="obj">
            <governor idx="7">mean</governor>
            <dependent idx="5">what</dependent>
          </dep>
          <dep type="nsubj">
            <governor idx="7">mean</governor>
            <dependent idx="6">I</dependent>
          </dep>
          <dep type="ccomp">
            <governor idx="4">know</governor>
            <dependent idx="7">mean</dependent>
          </dep>
          <dep type="punct">
            <governor idx="2">genetics</governor>
            <dependent idx="8">?</dependent>
          </dep>
        </dependencies>
        <dependencies type="collapsed-dependencies">
          <dep type="root">
            <governor idx="0">ROOT</governor>
            <dependent idx="2">genetics</dependent>
          </dep>
          <dep type="amod">
            <governor idx="2">genetics</governor>
            <dependent idx="1">Simple</dependent>
          </dep>
          <dep type="punct">
            <governor idx="2">genetics</governor>
            <dependent idx="3">...</dependent>
          </dep>
          <dep type="dep">
            <governor idx="2">genetics</governor>
            <dependent idx="4">know</dependent>
          </dep>
          <dep type="obj">
            <governor idx="7">mean</governor>
            <dependent idx="5">what</dependent>
          </dep>
          <dep type="nsubj">
            <governor idx="7">mean</governor>
            <dependent idx="6">I</dependent>
          </dep>
          <dep type="ccomp">
            <governor idx="4">know</governor>
            <dependent idx="7">mean</dependent>
          </dep>
          <dep type="punct">
            <governor idx="2">genetics</governor>
            <dependent idx="8">?</dependent>
          </dep>
        </dependencies>
        <dependencies type="collapsed-ccprocessed-dependencies">
          <dep type="root">
            <governor idx="0">ROOT</governor>
            <dependent idx="2">genetics</dependent>
          </dep>
          <dep type="amod">
            <governor idx="2">genetics</governor>
            <dependent idx="1">Simple</dependent>
          </dep>
          <dep type="punct">
            <governor idx="2">genetics</governor>
            <dependent idx="3">...</dependent>
          </dep>
          <dep type="dep">
            <governor idx="2">genetics</governor>
            <dependent idx="4">know</dependent>
          </dep>
          <dep type="obj">
            <governor idx="7">mean</governor>
            <dependent idx="5">what</dependent>
          </dep>
          <dep type="nsubj">
            <governor idx="7">mean</governor>
            <dependent idx="6">I</dependent>
          </dep>
          <dep type="ccomp">
            <governor idx="4">know</governor>
            <dependent idx="7">mean</dependent>
          </dep>
          <dep type="punct">
            <governor idx="2">genetics</governor>
            <dependent idx="8">?</dependent>
          </dep>
        </dependencies>
        <dependencies type="enhanced-dependencies">
          <dep type="root">
            <governor idx="0">ROOT</governor>
            <dependent idx="2">genetics</dependent>
          </dep>
          <dep type="amod">
            <governor idx="2">genetics</governor>
            <dependent idx="1">Simple</dependent>
          </dep>
          <dep type="punct">
            <governor idx="2">genetics</governor>
            <dependent idx="3">...</dependent>
          </dep>
          <dep type="dep">
            <governor idx="2">genetics</governor>
            <dependent idx="4">know</dependent>
          </dep>
          <dep type="obj">
            <governor idx="7">mean</governor>
            <dependent idx="5">what</dependent>
          </dep>
          <dep type="nsubj">
            <governor idx="7">mean</governor>
            <dependent idx="6">I</dependent>
          </dep>
          <dep type="ccomp">
            <governor idx="4">know</governor>
            <dependent idx="7">mean</dependent>
          </dep>
          <dep type="punct">
            <governor idx="2">genetics</governor>
            <dependent idx="8">?</dependent>
          </dep>
        </dependencies>
        <dependencies type="enhanced-plus-plus-dependencies">
          <dep type="root">
            <governor idx="0">ROOT</governor>
            <dependent idx="2">genetics</dependent>
          </dep>
          <dep type="amod">
            <governor idx="2">genetics</governor>
            <dependent idx="1">Simple</dependent>
          </dep>
          <dep type="punct">
            <governor idx="2">genetics</governor>
            <dependent idx="3">...</dependent>
          </dep>
          <dep type="dep">
            <governor idx="2">genetics</governor>
            <dependent idx="4">know</dependent>
          </dep>
          <dep type="obj">
            <governor idx="7">mean</governor>
            <dependent idx="5">what</dependent>
          </dep>
          <dep type="nsubj">
            <governor idx="7">mean</governor>
            <dependent idx="6">I</dependent>
          </dep>
          <dep type="ccomp">
            <governor idx="4">know</governor>
            <dependent idx="7">mean</dependent>
          </dep>
          <dep type="punct">
            <governor idx="2">genetics</governor>
            <dependent idx="8">?</dependent>
          </dep>
        </dependencies>
      </sentence>
      <sentence id="2">
        <tokens>
          <token id="1">
            <word>No</word>
            <lemma>no</lemma>
            <CharacterOffsetBegin>37</CharacterOffsetBegin>
            <CharacterOffsetEnd>39</CharacterOffsetEnd>
            <POS>UH</POS>
            <NER>O</NER>
          </token>
          <token id="2">
            <word>,</word>
            <lemma>,</lemma>
            <CharacterOffsetBegin>39</CharacterOffsetBegin>
            <CharacterOffsetEnd>40</CharacterOffsetEnd>
            <POS>,</POS>
            <NER>O</NER>
          </token>
          <token id="3">
            <word>you</word>
            <lemma>you</lemma>
            <CharacterOffsetBegin>41</CharacterOffsetBegin>
            <CharacterOffsetEnd>44</CharacterOffsetEnd>
            <POS>PRP</POS>
            <NER>O</NER>
          </token>
          <token id="4">
            <word>disgusting</word>
            <lemma>disgusting</lemma>
            <CharacterOffsetBegin>45</CharacterOffsetBegin>
            <CharacterOffsetEnd>55</CharacterOffsetEnd>
            <POS>JJ</POS>
            <NER>O</NER>
          </token>
          <token id="5">
            <word>racist</word>
            <lemma>racist</lemma>
            <CharacterOffsetBegin>56</CharacterOffsetBegin>
            <CharacterOffsetEnd>62</CharacterOffsetEnd>
            <POS>NN</POS>
            <NER>O</NER>
          </token>
          <token id="6">
            <word>.</word>
            <lemma>.</lemma>
            <CharacterOffsetBegin>62</CharacterOffsetBegin>
            <CharacterOffsetEnd>63</CharacterOffsetEnd>
            <POS>.</POS>
            <NER>O</NER>
          </token>
        </tokens>
        <parse>(ROOT (FRAG (INTJ (UH No)) (, ,) (NP (ADJP (NP (PRP you)) (JJ disgusting)) (NN racist)) (. .))) </parse>
        <dependencies type="basic-dependencies">
          <dep type="root">
            <governor idx="0">ROOT</governor>
            <dependent idx="5">racist</dependent>
          </dep>
          <dep type="discourse">
            <governor idx="5">racist</governor>
            <dependent idx="1">No</dependent>
          </dep>
          <dep type="punct">
            <governor idx="5">racist</governor>
            <dependent idx="2">,</dependent>
          </dep>
          <dep type="obl:npmod">
            <governor idx="4">disgusting</governor>
            <dependent idx="3">you</dependent>
          </dep>
          <dep type="amod">
            <governor idx="5">racist</governor>
            <dependent idx="4">disgusting</dependent>
          </dep>
          <dep type="punct">
            <governor idx="5">racist</governor>
            <dependent idx="6">.</dependent>
          </dep>
        </dependencies>
        <dependencies type="collapsed-dependencies">
          <dep type="root">
            <governor idx="0">ROOT</governor>
            <dependent idx="5">racist</dependent>
          </dep>
          <dep type="discourse">
            <governor idx="5">racist</governor>
            <dependent idx="1">No</dependent>
          </dep>
          <dep type="punct">
            <governor idx="5">racist</governor>
            <dependent idx="2">,</dependent>
          </dep>
          <dep type="obl:npmod">
            <governor idx="4">disgusting</governor>
            <dependent idx="3">you</dependent>
          </dep>
          <dep type="amod">
            <governor idx="5">racist</governor>
            <dependent idx="4">disgusting</dependent>
          </dep>
          <dep type="punct">
            <governor idx="5">racist</governor>
            <dependent idx="6">.</dependent>
          </dep>
        </dependencies>
        <dependencies type="collapsed-ccprocessed-dependencies">
          <dep type="root">
            <governor idx="0">ROOT</governor>
            <dependent idx="5">racist</dependent>
          </dep>
          <dep type="discourse">
            <governor idx="5">racist</governor>
            <dependent idx="1">No</dependent>
          </dep>
          <dep type="punct">
            <governor idx="5">racist</governor>
            <dependent idx="2">,</dependent>
          </dep>
          <dep type="obl:npmod">
            <governor idx="4">disgusting</governor>
            <dependent idx="3">you</dependent>
          </dep>
          <dep type="amod">
            <governor idx="5">racist</governor>
            <dependent idx="4">disgusting</dependent>
          </dep>
          <dep type="punct">
            <governor idx="5">racist</governor>
            <dependent idx="6">.</dependent>
          </dep>
        </dependencies>
        <dependencies type="enhanced-dependencies">
          <dep type="root">
            <governor idx="0">ROOT</governor>
            <dependent idx="5">racist</dependent>
          </dep>
          <dep type="discourse">
            <governor idx="5">racist</governor>
            <dependent idx="1">No</dependent>
          </dep>
          <dep type="punct">
            <governor idx="5">racist</governor>
            <dependent idx="2">,</dependent>
          </dep>
          <dep type="obl:npmod">
            <governor idx="4">disgusting</governor>
            <dependent idx="3">you</dependent>
          </dep>
          <dep type="amod">
            <governor idx="5">racist</governor>
            <dependent idx="4">disgusting</dependent>
          </dep>
          <dep type="punct">
            <governor idx="5">racist</governor>
            <dependent idx="6">.</dependent>
          </dep>
        </dependencies>
        <dependencies type="enhanced-plus-plus-dependencies">
          <dep type="root">
            <governor idx="0">ROOT</governor>
            <dependent idx="5">racist</dependent>
          </dep>
          <dep type="discourse">
            <governor idx="5">racist</governor>
            <dependent idx="1">No</dependent>
          </dep>
          <dep type="punct">
            <governor idx="5">racist</governor>
            <dependent idx="2">,</dependent>
          </dep>
          <dep type="obl:npmod">
            <governor idx="4">disgusting</governor>
            <dependent idx="3">you</dependent>
          </dep>
          <dep type="amod">
            <governor idx="5">racist</governor>
            <dependent idx="4">disgusting</dependent>
          </dep>
          <dep type="punct">
            <governor idx="5">racist</governor>
            <dependent idx="6">.</dependent>
          </dep>
        </dependencies>
      </sentence>
    </sentences>
  </document>
</root>
